compare_faces/__init__.py
compare_faces/comparation.py
compare_faces/io.py
compare_faces/load_img.py
compare_faces/plot.py
face_picture_comparator/__init__.py
face_picture_comparator/comparation.py
face_picture_comparator/load_img.py
face_picture_comparator/plot.py
face_picture_comparator-0.0.4.dist-info/METADATA
face_picture_comparator-0.0.4.dist-info/WHEEL
face_picture_comparator-0.0.4.dist-info/top_level.txt
face_picture_comparator-0.0.4.dist-info/RECORD
