Metadata-Version: 2.1
Name: face-picture-comparator
Version: 0.0.4
Summary: Two face comparison pack
Home-page: https://github.com/Ronaldo-Nunes/Cursos/tree/main/Geracao-Tech-Unimed-BH-Ciencia-Dados/compare-faces-package
Author: Ronaldo Nunes
Author-email: projetoftnunes@gmail.com
License: UNKNOWN
Platform: UNKNOWN
Requires-Python: >=3.8
Requires-Dist: opencv-python
Requires-Dist: matplotlib
Requires-Dist: face-recognition
